AUTHORS.md
MANIFEST.in
README.md
setup.cfg
setup.py
djangocms_youtube_lazyload/__init__.py
djangocms_youtube_lazyload/cms_plugins.py
djangocms_youtube_lazyload/conf.py
djangocms_youtube_lazyload/exceptions.py
djangocms_youtube_lazyload/forms.py
djangocms_youtube_lazyload/models.py
djangocms_youtube_lazyload/utils.py
djangocms_youtube_lazyload/widgets.py
djangocms_youtube_lazyload.egg-info/PKG-INFO
djangocms_youtube_lazyload.egg-info/SOURCES.txt
djangocms_youtube_lazyload.egg-info/dependency_links.txt
djangocms_youtube_lazyload.egg-info/not-zip-safe
djangocms_youtube_lazyload.egg-info/requires.txt
djangocms_youtube_lazyload.egg-info/top_level.txt
djangocms_youtube_lazyload/migrations/0001_initial.py
djangocms_youtube_lazyload/migrations/__init__.py
djangocms_youtube_lazyload/static/djangocms_youtube_lazyload/djangocms_youtube_lazyload.css
djangocms_youtube_lazyload/static/djangocms_youtube_lazyload/jquery.yt-player.js
djangocms_youtube_lazyload/static/djangocms_youtube_lazyload/greensock-js/TweenMax.js
djangocms_youtube_lazyload/static/djangocms_youtube_lazyload/greensock-js/TweenMax.min.js
djangocms_youtube_lazyload/templates/djangocms_youtube_lazyload/cms_youtube_change.html
djangocms_youtube_lazyload/templates/djangocms_youtube_lazyload/video.html