Metadata-Version: 2.1
Name: djangocms-youtube-lazyload
Version: 1.0.7
Summary: DjangoCMS YouTube video embed plugin with minimal impact
Home-page: https://github.com/jeroenpeters1986/djangocms-youtube-lazyload
Author: Jeroen Peters
Author-email: jeroenpeters1986@gmail.com
License: BSD
Keywords: djangocms-youtube-lazyload,YouTube,django-cms,youtube embed,video embedding,cmsplugin,lazyload,cmsplugin-youtube,djangocms-youtube,sitespeed
Platform: UNKNOWN
Classifier: Development Status :: 5 - Production/Stable
Classifier: Framework :: Django
Classifier: Framework :: Django :: 1.11
Classifier: Framework :: Django :: 2.2
Classifier: Programming Language :: Python :: 2.7
Classifier: Programming Language :: Python :: 3
Classifier: Programming Language :: Python :: 3.4
Classifier: Programming Language :: Python :: 3.5
Classifier: Programming Language :: Python :: 3.6
Classifier: Programming Language :: Python :: 3.7
Classifier: Programming Language :: Python :: 3.8
Classifier: Programming Language :: Python :: 3.9
Classifier: Framework :: Django CMS
Classifier: Framework :: Django CMS :: 3.6
Classifier: Framework :: Django CMS :: 3.7
Classifier: Framework :: Django CMS :: 3.8
Classifier: Intended Audience :: Developers
Classifier: License :: OSI Approved :: BSD License
Classifier: Natural Language :: English
